qed/__init__.py
qed/qed.py
uamc_qed-1.0.2.dist-info/LICENSE
uamc_qed-1.0.2.dist-info/METADATA
uamc_qed-1.0.2.dist-info/WHEEL
uamc_qed-1.0.2.dist-info/top_level.txt
uamc_qed-1.0.2.dist-info/RECORD
