Metadata-Version: 2.1
Name: uamc-qed
Version: 1.0.2
Summary: Python implementation of the QED descriptor (Quantitative Estimation of Druglikeness)
Home-page: https://github.com/UAMCAntwerpen/qed
Author: Hans De Winter
Author-email: hans.dewinter@uantwerpen.be
License: UNKNOWN
Download-URL: https://github.com/UAMCAntwerpen/qed/releases/tag/1.0.2
Keywords: uamc,qed,rdkit,cheminformatics
Platform: UNKNOWN
Classifier: Development Status :: 5 - Production/Stable
Classifier: Environment :: Console
Classifier: Intended Audience :: Science/Research
Classifier: License :: Freeware
Classifier: Operating System :: POSIX :: Linux
Classifier: Operating System :: MacOS :: MacOS X
Classifier: Programming Language :: Python :: 3
Classifier: Topic :: Scientific/Engineering :: Chemistry
Classifier: Topic :: Software Development :: Libraries :: Python Modules
Requires-Python: >=3.6
